appsquared/src/APPSquared_qxa4/120loop_check.py
appsquared/src/APPSquared_qxa4/150loop_check.py
appsquared/src/APPSquared_qxa4/160loop_check.py
appsquared/src/APPSquared_qxa4/190loop_check.py
appsquared/src/APPSquared_qxa4/Ca_check.py
appsquared/src/APPSquared_qxa4/Cb_check.py
appsquared/src/APPSquared_qxa4/H3_rbs_check.py
appsquared/src/APPSquared_qxa4/KM_check.py
appsquared/src/APPSquared_qxa4/Sa_check.py
appsquared/src/APPSquared_qxa4/Sb_check.py
appsquared/src/APPSquared_qxa4/__init__.py
appsquared/src/APPSquared_qxa4/contact_diffs.py
appsquared/src/APPSquared_qxa4/glyc.py
appsquared/src/APPSquared_qxa4/ligprep_3-sialyl-out.maegz
appsquared/src/APPSquared_qxa4/ligprep_6-sialyl-out.maegz
appsquared/src/APPSquared_qxa4/prep_Darwin_6_2021_trimer.pdb
appsquared/src/APPSquared_qxa4/prep_Wisconsin_588_trimer.mae
appsquared/src/APPSquared_qxa4/prep_Wisconsin_588_trimer.pdb
appsquared/src/APPSquared_qxa4/rbs_check.py
appsquared/src/APPSquared_qxa4/rbs_networked.py
appsquared/src/APPSquared_qxa4/run_Bvic_BCP.sh
appsquared/src/APPSquared_qxa4/run_H1_BCP.sh
appsquared/src/APPSquared_qxa4/run_H3_BCP.sh
appsquared/src/APPSquared_qxa4/run_N2_BCP.sh
appsquared/src/APPSquared_qxa4/run_contactdiffs.sh
appsquared/src/APPSquared_qxa4/run_contactdiffs_H3.sh
appsquared/src/APPSquared_qxa4/run_glyc.sh
appsquared/src/APPSquared_qxa4/run_rosetta.sh
appsquared/src/APPSquared_qxa4/run_sasa.py
appsquared/src/APPSquared_qxa4/sin_check.py
appsquared/src/APPSquared_qxa4/siteA_check.py
appsquared/src/APPSquared_qxa4/siteB_check.py
appsquared/src/APPSquared_qxa4/siteC_check.py
appsquared/src/APPSquared_qxa4/siteD_check.py
appsquared/src/APPSquared_qxa4/siteE_check.py
appsquared-1.1.1.dist-info/LICENSE
appsquared-1.1.1.dist-info/METADATA
appsquared-1.1.1.dist-info/WHEEL
appsquared-1.1.1.dist-info/RECORD
